.gitignore
LICENSE.txt
MANIFEST.in
README.rst
setup.py
version.py
delegate/__init__.py
delegate/models.py
delegate/settings.py
delegate/tests.py
django_delegate.egg-info/PKG-INFO
django_delegate.egg-info/SOURCES.txt
django_delegate.egg-info/dependency_links.txt
django_delegate.egg-info/top_level.txt