Metadata-Version: 1.1
Name: django-delegate
Version: 0.3.0
Summary: 
